geogradev/__init__.py
geogradev/common.py
geogradev/geogradev.py
geogradev-1.1.2.dist-info/licenses/LICENSE
geogradev-1.1.2.dist-info/METADATA
geogradev-1.1.2.dist-info/WHEEL
geogradev-1.1.2.dist-info/entry_points.txt
geogradev-1.1.2.dist-info/top_level.txt
geogradev-1.1.2.dist-info/RECORD
